nornir_collection/__init__.py
nornir_collection/git.py
nornir_collection/utils.py
nornir_collection/batfish/__init__.py
nornir_collection/batfish/assert_config.py
nornir_collection/batfish/utils.py
nornir_collection/cisco/__init__.py
nornir_collection/cisco/configuration_management/__init__.py
nornir_collection/cisco/configuration_management/processor.py
nornir_collection/cisco/configuration_management/pyats.py
nornir_collection/cisco/configuration_management/utils.py
nornir_collection/cisco/configuration_management/cli/__init__.py
nornir_collection/cisco/configuration_management/cli/config_tasks.py
nornir_collection/cisco/configuration_management/cli/config_workflow.py
nornir_collection/cisco/configuration_management/cli/show_tasks.py
nornir_collection/cisco/configuration_management/netconf/__init__.py
nornir_collection/cisco/configuration_management/netconf/config_tasks.py
nornir_collection/cisco/configuration_management/netconf/config_workflow.py
nornir_collection/cisco/configuration_management/netconf/nr_cfg_iosxe_netconf.py
nornir_collection/cisco/configuration_management/netconf/nr_cfg_iosxe_testsprocessor.py
nornir_collection/cisco/configuration_management/netconf/ops_tasks.py
nornir_collection/cisco/configuration_management/restconf/__init__.py
nornir_collection/cisco/configuration_management/restconf/cisco_rpc.py
nornir_collection/cisco/configuration_management/restconf/config_workflow.py
nornir_collection/cisco/configuration_management/restconf/tasks.py
nornir_collection/cisco/software_upgrade/__init__.py
nornir_collection/cisco/software_upgrade/cisco_software_upgrade.py
nornir_collection/cisco/software_upgrade/utils.py
nornir_collection/cisco/support_api/__init__.py
nornir_collection/cisco/support_api/api_calls.py
nornir_collection/cisco/support_api/cisco_maintenance_report.py
nornir_collection/cisco/support_api/cisco_support.py
nornir_collection/cisco/support_api/reports.py
nornir_collection/cisco/support_api/utils.py
nornir_collection-0.0.51.dist-info/licenses/LICENSE
nornir_collection-0.0.51.dist-info/METADATA
nornir_collection-0.0.51.dist-info/WHEEL
nornir_collection-0.0.51.dist-info/top_level.txt
nornir_collection-0.0.51.dist-info/RECORD
