Metadata-Version: 2.4
Name: nornir-collection
Version: 0.0.51
Summary: Nornir-Collection contains network automation functions and complete IaC workflows with         Nornir and other python libraries. It contains Nornir tasks and general functions in Nornir style.
Author: Willi Kubny
Author-email: willi.kubny@gmail.ch
Classifier: Programming Language :: Python :: 3
Classifier: License :: OSI Approved :: MIT License
Classifier: Operating System :: OS Independent
Requires-Python: >=3.9
License-File: LICENSE
Requires-Dist: nornir==3.5.0
Requires-Dist: nornir-jinja2==0.2.0
Requires-Dist: nornir-salt==0.22.5
Requires-Dist: nornir-netmiko==1.0.1
Requires-Dist: nornir-scrapli==2024.7.30
Requires-Dist: scrapli-netconf==2024.1.30
Requires-Dist: nornir-utils==0.2.0
Requires-Dist: nornir-pyfgt==1.0.3
Requires-Dist: scrapli[ssh2]
Requires-Dist: scrapli[genie]
Requires-Dist: pynetbox==7.4.0
Requires-Dist: ipfabric==7.3.1
Requires-Dist: py-pure-client==1.51.0
Requires-Dist: python-nmap==0.7.1
Requires-Dist: pybatfish==2023.12.16.1270
Requires-Dist: requests==2.31.0
Requires-Dist: dnspython==2.8.0
Requires-Dist: pre-commit==3.6.0
Requires-Dist: pyyaml==6.0.1
Requires-Dist: pyfiglet==1.0.2
Requires-Dist: GitPython==3.1.45
Requires-Dist: python-dotenv==1.1.1
Requires-Dist: beautifultable==1.1.0
Requires-Dist: pandas==2.2.2
Requires-Dist: openpyxl==3.1.2
Requires-Dist: XlsxWriter==3.1.9
Requires-Dist: yaspin==3.0.1
Requires-Dist: rich==13.7.0
Requires-Dist: tabulate==0.9.0
Requires-Dist: ruff==0.9.2
Requires-Dist: yamllint==1.33.0
Requires-Dist: bandit==1.7.6
Requires-Dist: vulture==2.10
Dynamic: author
Dynamic: author-email
Dynamic: classifier
Dynamic: description
Dynamic: description-content-type
Dynamic: license-file
Dynamic: requires-dist
Dynamic: requires-python
Dynamic: summary
